{
    "id": "hf_jp-ii_aud_19931124",
    "pope_id": "john-paul-ii",
    "type": "audiences",
    "date": "",
    "title": "24 November 1993",
    "excerpt": {
        "it": "1. La Chiesa è santa e tutti i suoi membri sono chiamati alla santità. I laici partecipano alla santità della Chiesa, essendomembria pieno titolo della comunità cristiana: e questa partecipazione, che possiamo direontologica, alla santità della Chiesa, si traduce anche per i laici in un impegnoeticopersonale di santificazione. In questa capacità e in questa vocazione di santità, tutti i membri della Chiesa sono eguali (cf.Gal3, 28).",
        "es": "La vocación de los laicos a la santidad"
    },
    "metadata": {
        "vatican_urls": {
            "it": "https://www.vatican.va/content/john-paul-ii/it/audiences/1993/documents/hf_jp-ii_aud_19931124.html",
            "es": "https://www.vatican.va/content/john-paul-ii/es/audiences/1993/documents/hf_jp-ii_aud_19931124.html"
        },
        "raw_html": {
            "it": "<div class=\"documento\">\n<!-- CONTENUTO DOCUMENTO -->\n<!-- TESTO -->\n<div class=\"testo\">\n<div class=\"abstract text parbase vaticanrichtext\"><div class=\"clearfix\"></div></div>\n<div class=\"text parbase container vaticanrichtext\"><p align=\"center\"><font color=\"#663300\">GIOVANNI PAOLO II</font></p>\n<p align=\"center\"><b><i><font color=\"#663300\" size=\"4\">UDIENZA GENERALE</font></i></b></p>\n<p align=\"center\"><i><font color=\"#663300\">Mercoledì, 24 novembre 1993</font></i></p>\n<p> </p>\n<p>1. La Chiesa è santa e tutti i suoi membri sono chiamati alla santità. I laici partecipano alla santità della Chiesa, essendo <i>membri</i> a pieno titolo della comunità cristiana: e questa partecipazione, che possiamo dire <i> ontologica</i>, alla santità della Chiesa, si traduce anche per i laici in un impegno <i>etico</i> personale di santificazione. In questa capacità e in questa vocazione di santità, tutti i membri della Chiesa sono eguali (cf. <i>Gal</i> 3, 28). </p>\n<p>Il grado di santità personale non dipende dalla posizione occupata nella società e nemmeno nella Chiesa, ma unicamente dal grado di carità vissuta (cf. <i>1 Cor</i> 13). Un laico che accoglie generosamente la carità divina nel suo cuore e nella sua vita è più santo di un Sacerdote o un Vescovo che l’accolgono in modo mediocre. </p>\n<p>2. La santità cristiana ha la sua radice nell’adesione a Cristo per mezzo della fede e del battesimo. Questo sacramento sta all’origine della comunione ecclesiale nella santità. È ciò che traspare dal testo paolino: “Un solo Signore, una sola fede, un solo battesimo” (<i>Ef</i> 4, 5), citato dal Concilio Vaticano II, che ne trae l’affermazione sulla comunanza che lega i cristiani in Cristo e nella Chiesa (<i><a href=\"http://www.vatican.va/archive/hist_councils/ii_vatican_council/documents/vat-ii_const_19641121_lumen-gentium_it.html\">Lumen Gentium</a></i>, 32). In questa partecipazione alla vita di Cristo mediante il Battesimo s’innesta la santità ontologica, ecclesiologica ed etica di ogni credente, chierico o laico che sia. </p>\n<p>Afferma il Concilio: “I seguaci di Cristo, chiamati da Dio e giustificati in Gesù Cristo non secondo le loro opere, ma secondo il disegno e la grazia di Lui, nel battesimo della fede sono stati fatti veramente figli di Dio e compartecipi della natura divina, e perciò realmente santi” (LG 40). La santità è appartenenza a Dio; questa appartenenza si attua nel Battesimo, quando Cristo prende possesso dell’essere umano per renderlo “partecipe della natura divina” (cf. <i>2 Pt</i> 1, 4) che è in lui in forza dell’Incarnazione (cf. <i>Summa theologiae</i>, III, q. 7, a. 13; q. 8, a. 5). Cristo diventa così, veramente, come è stato detto, “vita dell’anima”. Il carattere sacramentale impresso nell’uomo dal Battesimo è il segno e il vincolo della consacrazione a Dio. Ecco perché Paolo, parlando dei battezzati, li chiama “i santi” (cf. <i>Rm</i> 1, 7; <i>1 Cor</i> 1, 2; <i>2 Cor</i> 1, 1; ecc.). </p>\n<p>3. Ma, come abbiamo detto, da questa santità ontologica deriva l’impegno della santità etica. Tutti devono, come dice il Concilio, “con l’aiuto di Dio, mantenere e perfezionare, vivendola, la santità che hanno ricevuto” (LG 40). Tutti devono tendere alla santità, perché ne hanno già il germe in loro stessi; devono sviluppare questa santità che è stata loro concessa. Tutti devono vivere “come si addice ai santi” (<i>Ef</i> 5, 3) e rivestirsi, “come amati di Dio, santi e diletti, di sentimenti di misericordia, di bontà, di umiltà, di mansuetudine, di pazienza” (<i>Col</i> 3, 12). La santità che possiedono non li preserva dalle tentazioni né da ogni colpa, perché rimane nei battezzati la persistente fragilità della natura umana nella vita presente. Il Concilio di Trento insegna, al riguardo, che nessuno può per tutta la vita evitare ogni peccato, anche veniale, senza uno speciale privilegio di Dio, come la Chiesa crede essere avvenuto per la Vergine Santissima (cf. Denz. 1573). Ciò induce alla preghiera per ottenere dal Signore una grazia sempre nuova, la perseveranza nel bene, e il perdono dei peccati: “Rimetti a noi i nostri debiti” (<i>Mt</i> 6, 12). </p>\n<p>4. Secondo il Concilio, tutti i seguaci di Cristo, anche i laici, sono chiamati alla perfezione della carità (LG 40). La tendenza alla perfezione non è un privilegio di alcuni, ma un impegno di tutti i membri della Chiesa. E impegno per la perfezione cristiana significa cammino perseverante verso la santità. Come dice il Concilio, “il Signore Gesù, Maestro e Modello divino di ogni perfezione, a tutti e ai singoli suoi discepoli di qualsiasi condizione ha predicato la santità della vita, di cui Egli stesso è autore e perfezionatore: “Siate dunque perfetti come è perfetto il vostro Padre celeste” (<i>Mt</i> 5, 48)” (LG 40). E perciò: “Tutti i fedeli di qualsiasi stato o grado sono chiamati alla pienezza della vita cristiana e alla perfezione della carità” (<i>Ivi</i>). Proprio grazie alla santificazione di ciascuno viene introdotta una nuova perfezione umana nella società terrena: come diceva la Serva di Dio Elisabetta Leseur, “ogni anima che si eleva, eleva con sé il mondo”. Il Concilio insegna che “da questa santità è promosso, anche nella società terrena, un tenore di vita più umano” (<i>Ivi</i>). </p>\n<p>5. A questo punto occorre notare che la ricchezza infinita della grazia di Cristo, partecipata agli uomini, si traduce in una quantità e varietà di doni, con i quali ciascuno può servire e beneficare gli altri nell’unico corpo della Chiesa. Era la raccomandazione di San Pietro ai cristiani disseminati nell’Asia Minore, quando, esortandoli alla santità, scriveva: “Ciascuno viva secondo la grazia ricevuta, mettendola a servizio degli altri, come buoni amministratori di una multiforme grazia di Dio” (<i>1 Pt</i> 4, 10). </p>\n<p>Anche il Concilio Vaticano II dice che “nei vari generi di vita e nei vari uffici un’unica santità è coltivata da quanti sono mossi dallo Spirito di Dio” (LG 41). Così esso ricorda la via di santità per i Vescovi, i Sacerdoti, i Diaconi, i Chierici che aspirano a diventare ministri di Cristo, e “quei laici eletti da Dio, i quali sono chiamati dal Vescovo perché si diano più completamente alle opere apostoliche”. Ma più espressamente esso considera la via di santità per i cristiani impegnati nel matrimonio: “I coniugi e i genitori cristiani, seguendo la loro propria via, devono con costante amore sostenersi a vicenda nella grazia per tutta la vita, e istruire nella dottrina cristiana e nelle virtù evangeliche la prole, che hanno amorosamente accettata da Dio. Così infatti offrono a tutti l’esempio di un amore instancabile e generoso, edificano il fraterno consorzio della carità, e diventano testimoni e cooperatori della fecondità della Madre Chiesa, in segno e partecipazione di quell’amore col quale Cristo amò la sua Sposa e si è dato per lei” (<i>Ivi</i>). </p>\n<p>Il discorso può e deve essere esteso alla condizione delle persone che vivono sole, o per libera scelta o per eventi e circostanze particolari: come i celibi e le nubili, i vedovi e le vedove, i separati e i lontani. Per tutti vale la chiamata divina alla santità, attuata in forma di carità. Il discorso può e deve essere altresì esteso, come nel Sinodo del 1987 (cf. <i> <a href=\"/content/john-paul-ii/it/apost_exhortations/documents/hf_jp-ii_exh_30121988_christifideles-laici.html\"> Chistifideles Laici</a></i>, 17), a coloro che nell’ordinaria vita professionale e nel quotidiano lavoro operano per il bene dei fratelli e il progresso della società, a imitazione di Gesù lavoratore. Può e deve essere esteso, infine, a tutti coloro che, come dice il Concilio, “sono oppressi dalla povertà, dalla debolezza, e dalle varie tribolazioni, malattie e infermità o soffrono persecuzioni per la giustizia”: essi sono “uniti in modo speciale a Cristo sofferente per la salute del mondo” (LG 41). </p>\n<p>6. Molteplici sono dunque gli aspetti e le forme della santità cristiana che sono aperti ai laici, nelle loro varie condizioni di vita, nelle quali sono chiamati a imitare Cristo, e possono ricevere da Lui la grazia necessaria per adempiere la loro missione nel mondo. Tutti sono invitati da Dio a percorrere la via della santità e ad attirare su questa via i loro compagni di vita e di lavoro nel mondo delle cose temporali.  </p>\n<hr>\n<p><i>Ai pellegrini di lingua francese </i> </p>\n<p>Chers frères et sœurs, </p>\n<p>Je salue avec plaisir les personnes de langue française ici présentes, et notamment le groupe d’employés des sanctuaires de Lourdes qui se dévouent au service des pèlerins de Notre–Dame. A tous, je donne de grand cœur ma Bénédiction Apostolique.  </p>\n<p><i>Ai fedeli di lingua inglese </i> </p>\n<p>Dear Brothers and Sisters, </p>\n<p>I gladly greet the English–speaking pilgrims and visitors, especially the members of the General Chapter of the Daughters of our Lady of the Sacred Heart, and the Students of Church History from the Archdiocese of Melbourne in Australia. </p>\n<p>Upon all present I invoke the abundant grace of our Lord and Saviour Jesus Christ. </p>\n<p><i>Ai pellegrini del Giappone </i> </p>\n<p>Sia lodato Gesù Cristo! </p>\n<p>Dilettissimi pellegrini del Giappone. </p>\n<p>Sta ormai terminando l’anno liturgico della Chiesa e sta per iniziare il nuovo. Esprimo il desiderio che voi tutti possiate inserirvi più profondamente nella vita della Chiesa, sotto la guida della Madonna Santissima. Questo è un augurio, che affido alla stessa Madre di Dio e Madre nostra, mentre imparto a ciascuno di voi la mia Benedizione Apostolica. </p>\n<p>Sia lodato Gesù Cristo!  </p>\n<p><i>Ai fedeli di lingua tedesca </i> </p>\n<p>Liebe Schwestern und Brüder! </p>\n<p>Mit dieser kurzen Betrachtung heibe ich alle deutschsprachigen Pilger und Besucher sehr herzlich willkommen. Mein besonderer Grub gilt den zum Generalkapitel in Rom versammelten Marienschwestern von der Unbefleckten Empfängnis. </p>\n<p>Euch allen, liebe Schwestern und Brüder, Euren lieben Angehörigen daheim sowie all jenen, die uns in diesem Augenblick geistlich verbunden sind, erteile ich von Herzen meinen Apostolischen Segen. </p>\n<p><i>Ai pellegrini di espressione spagnola </i> </p>\n<p>Amadísimos hermanos y hermanas, </p>\n<p>Saludo ahora con gran afecto a todos los peregrinos y visitantes de los distintos países de América Latina y de España. En particular, al grupo de sacerdotes latinoamericanos, que hacen en Roma un curso de espiritualidad sacerdotal. </p>\n<p>A todos bendigo de corazón. </p>\n<p><i>Ai fedeli di lingua portoghese </i></p>\n<p>Amados peregrinos de língua portuguesa, </p>\n<p>Caríssimos Irmãos e Irmãs, perseverai na obra da vossa santificação, lembrados de que uma alma que se eleva, eleva o mundo. Que o amor de Deus reine nos vossos corações, e a terra será nova! As maiores felicidades para vós e para os vossos queridos, com a Bênção que vos dou em nome do Senhor. </p>\n<p><i>Ai pellegrini polacchi </i></p>\n<p>Pozdrawiam pielgrzymów z Polski: ze Skawiny – parafia św. Judy Tadeusza, z Brzeska – parafia Miłosierdzia Bożego, z Pszowa – chór “ Cecylia ” z sanktuarium Matki Bożej, prócz tego Kapituła Generalna sióstr ze Zgromadzenia Maryi Niepokalanej oraz różne grupy turystyczne: z Krakowa–Gdowa – “ Krak ”, z Opola – “ Itaka ”, z Petersburga – “ Voyager ” oraz z Miejskiej Górki grupa “ Anda ”; na koniec wszystkich innych uczestników audiencji, pochodzących z kraju oraz z emigracji. </p>\n<p><i>Ai gruppi di fedeli italiani</i> </p>\n<p>Accolgo con gioia il folto gruppo di Religiose operatrici sanitarie negli ospedali o al servizio delle Consorelle anziane e malate. Carissime, il Convegno al quale state partecipando sia occasione di valido aggiornamento e di interiore rigenerazione, nello scambio delle esperienze e nella preghiera comune. Portate a quanti sono affidati alle vostre cure la mia affettuosa benedizione.  </p>\n<p><i>Ai giovani, agli ammalati e agli sposi novelli </i> </p>\n<p>Rivolgo ora il mio cordiale saluto ai <i>giovani</i>, agli <i>ammalati</i> e agli <i>sposi novelli</i> presenti. La prossima domenica segnerà l’inizio dell’Avvento, il periodo liturgico che precede e prepara la celebrazione del Santo Natale. Auguro a ciascuno di voi di aprire il cuore al Signore, per preparare la strada a Colui che viene a colmare con la luce della sua presenza ogni nostra umana debolezza. Vi accompagni in questo impegno anche la mia apostolica benedizione. </p>\n<p align=\"center\">  </p>\n<p align=\"center\"> <font color=\"#663300\" size=\"3\">© Copyright 1993 - Libreria Editrice Vaticana</font></p>\n<p align=\"justify\">  </p><div class=\"clearfix\"></div></hr></div>\n</div>\n<!-- /TESTO -->\n<br style=\"clear: both;\"/>\n<hr/>\n<p align=\"center\"><font color=\"#663300\">Copyright © Dicastero per la Comunicazione - Libreria Editrice Vaticana</font></p>\n<!-- /CONTENUTO DOCUMENTO -->\n</div>",
            "es": "<div class=\"documento\">\n<!-- CONTENUTO DOCUMENTO -->\n<!-- TESTO -->\n<div class=\"testo\">\n<div class=\"abstract text parbase vaticanrichtext\"><div class=\"clearfix\"></div></div>\n<div class=\"text parbase container vaticanrichtext\"><p align=\"center\"><font color=\"#663300\">JUAN PABLO II</font></p>\n<p align=\"center\"><font color=\"#663300\"><i><b><font size=\"4\"> AUDIENCIA GENERAL</font></b></i><br><br/><i>Miércoles 24 de noviembre de 1993</i></br></font></p>\n<p>  </p>\n<p> <b>La vocación de los laicos a la santidad </b></p>\n<p align=\"right\"> <i>(Lectura: <br/>1ra. carta de san Pedro, capítulo 1, versículos 14-16)</i> </p>\n<p> 1. La Iglesia es santa y todos sus miembros están llamados a la santidad. Los laicos participan en la santidad de la Iglesia, al ser <i>miembros</i> con pleno derecho de la comunidad cristiana; y esta participación, que podríamos definir <i>ontológica</i>, en la santidad de la Iglesia, se traduce también para los laicos en un compromiso <i>ético</i> personal de santificación. En esta capacidad y en esta vocación de santidad, todos los miembros de la Iglesia son iguales (cf. <i>Ga</i> 3, 28).</p>\n<p> El grado de santidad personal no depende de la posición que se ocupa en la sociedad o en la Iglesia, sino únicamente del grado de caridad que se vive (cf. I <i>Co</i> 13). Un laico que acepta generosamente la caridad divina en su corazón y en su vida es más santo que un sacerdote o un obispo que la aceptan de modo mediocre.</p>\n<p> 2. La santidad cristiana tiene su raíz en la adhesión a Cristo por medio de la fe y del bautismo. Este sacramento es la fuente de la comunión eclesial en la santidad. Es lo que pone de relieve el texto paulino: «Un solo Señor, una sola fe, un solo bautismo» (<i>Ef</i> 4, 5), citado por el concilio Vaticano II, que de ahí deduce la afirmación sobre la comunión que vincula a los cristianos en Cristo y en la Iglesia (<i><a href=\"http://www.vatican.va/archive/hist_councils/ii_vatican_council/documents/vat-ii_const_19641121_lumen-gentium_sp.html\">Lumen gentium</a></i>, 32). En esta participación en la vida de Cristo mediante el bautismo se injerta la santidad ontológica, eclesiológica y ética de todo creyente, sea clérigo o laico.</p>\n<p> El Concilio afirma: «Los seguidores de Cristo, llamados por Dios no en razón de sus obras, sino en virtud del designio y gracia divinos y justificados en el Señor Jesús, han sido hechos por el bautismo, sacramento de la fe, verdaderos hijos de Dios y partícipes de la divina naturaleza, y, por lo mismo, realmente santos» (<i><a href=\"http://www.vatican.va/archive/hist_councils/ii_vatican_council/documents/vat-ii_const_19641121_lumen-gentium_sp.html\">Lumen gentium</a></i>, 40). La santidad es pertenencia a Dios, y esta pertenencia se realiza en el bautismo, cuando Cristo toma posesión del ser humano para hacerlo «partícipe de la naturaleza divina» (cf. 2 <i>Pe</i> 1, 4) que hay en él en virtud de la Encarnación (cf. <i>Summa Theol</i>. III, q. 7 a. 13; q. 8, a. 5). Cristo se convierte así de verdad, como se ha dicho, en <i>vida del alma</i>. El carácter sacramental impreso en el hombre por el bautismo es el signo y el vínculo de la consagración a Dios. Por eso san Pablo hablando de los bautizados los llama «los santos» (cf. <i>Rm</i> 1, 7; <i>1 Co</i> 1; <i>2 Co</i> 1, 1; etc.).</p>\n<p> 3. Pero, como hemos dicho, de esta santidad ontológica brota el compromiso de la santidad ética. Como dice el Concilio, «es necesario que todos, con la ayuda de Dios, conserven y perfeccionen en su vida la santificación que recibieron» (<i><a href=\"http://www.vatican.va/archive/hist_councils/ii_vatican_council/documents/vat-ii_const_19641121_lumen-gentium_sp.html\">Lumen gentium</a></i>, 40). Todos deben tender a la santidad, porque ya tienen en sí mismos el germen; deben desarrollar esa santidad que se les ha concedido. Todos deben vivir «como conviene a los santos» (<i>Ef</i> 5, 3) y revestirse, «como elegidos de Dios, santos y amados, de entrañas de misericordia de bondad, humildad, mansedumbre, paciencia» (<i>Col</i> 3, 12). La santidad que poseen no les libra de las tentaciones ni de las culpas, porque en los bautizados sigue existiendo la fragilidad de la naturaleza humana en la vida presente. El concilio de Trento enseña, al respecto que nadie puede evitar durante toda su vida el pecado incluso venial, sin un privilegio especial de Dios, como la Iglesia cree que acaeció con la santísima Virgen (cf. <i>Denz-S</i>., 1.573). Eso nos impulsa a orar para obtener del Señor una gracia siempre nueva, la perseverancia en el bien y el perdón de los pecados: «Perdona nuestras ofensas»(<i>Mt</i> 6, 12).</p>\n<p> 4. Según el Concilio, todos los seguidores de Cristo, incluidos los laicos, están llamados a la perfección de la caridad (<i><a href=\"http://www.vatican.va/archive/hist_councils/ii_vatican_council/documents/vat-ii_const_19641121_lumen-gentium_sp.html\">Lumen gentium</a></i>, 40). La tendencia a la perfección no es privilegio de algunos, sino compromiso de todos los miembros de la Iglesia. Y compromiso por la perfección cristiana significa camino perseverante hacia la santidad. Como dice el Concilio, «el divino Maestro y modelo de toda perfección, el Señor Jesús, predicó a todos y cada uno de sus discípulos, cualquiera que fuese su condición, la santidad de vida, de la que él es iniciador y consumador: \"Sed, pues, vosotros perfectos, como vuestro Padre celestial es perfecto\" (<i>Mt</i> 5, 48)» (ib.). Por ello: «todos los fieles, de cualquier estado o condición, están llamados a la plenitud de la vida cristiana y a la perfección de la caridad» (<i>ib</i>.). Precisamente gracias a la santificación de cada uno se introduce una nueva perfección humana en la sociedad terrena: como decía la sierva de Dios Isabel Leseur, «toda alma que se eleva consigo el mundo». EL Concilio enseña que «esta santidad suscita un nivel de vida más humano, incluso en la sociedad terrena» (<i>ib</i>.).</p>\n<p> 5. Conviene observar aquí que la riqueza infinita de la gracia de Cristo, participada a los hombres, se traduce en una gran cantidad y variedad de dones, con los que cada uno puede servir y beneficiar a los demás en el único cuerpo de la Iglesia. Era la recomendación de san Pedro a los cristianos esparcidos en Asia Menor cuando, exhortándolos a la santidad, escribía: «Que cada cual ponga al servicio de los demás la gracia que ha recibido, como buenos administradores de las diversas gracias de Dios» (<i>1 P</i> 4, 10).</p>\n<p> También el concilio Vaticano II dice que «una misma es la santidad que cultivan, en los múltiples géneros de vida y ocupaciones, todos los que son guiados por el Espíritu de Dios» (<i><a href=\"http://www.vatican.va/archive/hist_councils/ii_vatican_council/documents/vat-ii_const_19641121_lumen-gentium_sp.html\">Lumen gentium</a></i>, 41). Así recuerda el camino de santidad para los obispos, los sacerdotes, los diáconos, los clérigos que aspiran a convertirse en ministros de Cristo, y «aquellos laicos elegidos por Dios que son llamados por el obispo para que se entreguen por completo a las tareas apostólicas» (<i>ib</i>.). Pero de forma más expresa considera el camino de santidad para los laicos cristianos comprometidos en el matrimonio: «Los esposos y padres cristianos, siguiendo su propio camino, mediante la fidelidad en el amor, deben sostenerse mutuamente en la gracia a lo largo de toda la vida e inculcar la doctrina cristiana y las virtudes evangélicas a los hijos amorosamente recibidos de Dios. De esta manera ofrecen a todos el ejemplo de un incansable y generoso amor, contribuyen al establecimiento de la fraternidad en la caridad y se constituyen en testigos y colaboradores de la fecundidad de la madre Iglesia, como símbolo y participación de aquel amor con que Cristo amó a su Esposa y se entregó a sí mismo por ella» (<i>ib</i>.).</p>\n<p> Lo mismo se puede y debe decir de las personas que viven solas, o por libre elección o por acontecimientos y circunstancias particulares: como los célibes o las núbiles, los viudos y las viudas, los separados y los alejados. Para todos vale la llamada divina a la santidad, realizada en forma de caridad. Y lo mismo se puede y debe decir, como afirma el Sínodo de 1987 (cf. <i> <a href=\"/content/john-paul-ii/es/apost_exhortations/documents/hf_jp-ii_exh_30121988_christifideles-laici.html\">Christifideles laici</a></i>, 17), de aquellos que en la vida profesional ordinaria y en el trabajo cotidiano actúan por el bien de sus hermanos y el progreso de la sociedad, a imitación de Jesús obrero. Y lo mismo se puede y debe decir, por último, de todos los que, como dice el Concilio, «se encuentran oprimidos por la pobreza, la enfermedad, los achaques y otros muchos sufrimientos o los que padecen persecución por la justicia»: éstos «están especialmente unidos a Cristo, paciente por la salvación del mundo» (<i><a href=\"http://www.vatican.va/archive/hist_councils/ii_vatican_council/documents/vat-ii_const_19641121_lumen-gentium_sp.html\">Lumen gentium</a></i>, 41).</p>\n<p> 6. Son muchos, por consiguiente, los aspectos y las formas de la santidad cristiana que están al alcance de los laicos, en sus diversas condiciones de vida, en las que están llamados a imitar a Cristo, y pueden recibir de él la gracia necesaria para cumplir su misión en el mundo. Todos están invitados por Dios a recorrer el camino de la santidad y a atraer hacia este camino a sus compañeros de vida y de trabajo en el mundo de las cosas temporales.</p>\n<p align=\"center\">  * * *</p>\n<p> <b>Saludos</b></p>\n<p> <i>Amadísimos hermanos y hermanas:</i></p>\n<p> Saludo ahora con gran afecto a todos los peregrinos y visitantes de los distintos países de América Latina y de España. En particular, al grupo de sacerdotes latinoamericanos que hacen en Roma un curso de espiritualidad sacerdotal.</p>\n<p> A todos bendigo de corazón</p><div class=\"clearfix\"></div></div>\n</div>\n<!-- /TESTO -->\n<br style=\"clear: both;\"/>\n<hr/>\n<p align=\"center\"><font color=\"#663300\">Copyright © Dicastero per la Comunicazione - Libreria Editrice Vaticana</font></p>\n<!-- /CONTENUTO DOCUMENTO -->\n</div>"
        }
    }
}