{
    "id": "hf_jp-ii_spe_19880624_mauthausen-linz",
    "pope_id": "john-paul-ii",
    "type": "speeches",
    "date": "1988-06-24",
    "title": "Meeting with some survivors of the Mauthausen Concentration Camp, in the vicinity of Linz",
    "excerpt": {
        "de": "1. Es ist schwer, ausdrucksstärkere Worte zu finden, als wir sie soeben aus den Klageliedern vernommen haben, die von der Überlieferung dem Propheten Jeremia zugeschrieben werden.",
        "it": "1. È difficile trovare espressioni più forti, dopo aver appena ascoltato le lamentazioni che la tradizione attribuisce al profeta Geremia."
    },
    "metadata": {
        "vatican_urls": {
            "de": "https://www.vatican.va/content/john-paul-ii/de/speeches/1988/june/documents/hf_jp-ii_spe_19880624_mauthausen-linz.html",
            "it": "https://www.vatican.va/content/john-paul-ii/it/speeches/1988/june/documents/hf_jp-ii_spe_19880624_mauthausen-linz.html"
        },
        "raw_html": {
            "de": "<div class=\"documento\">\n<!-- CONTENUTO DOCUMENTO -->\n<!-- TESTO -->\n<div class=\"testo\">\n<div class=\"abstract text parbase vaticanrichtext\"><div class=\"clearfix\"></div></div>\n<div class=\"text parbase container vaticanrichtext\"><p align=\"center\"><font color=\"#663300\">PASTORALBESUCH IN ÖSTERREICH</font></p>\n<p align=\"center\"><b><i><font color=\"#663300\" size=\"4\">ANSPRACHE VON JOHANNES PAUL II. <br> <font face=\"Times New Roman\">AN EINIGE ÜBERLEBENDE <br/> IM KONZENTRATIONSLAGER MAUTHAUSEN</font></br></font></i></b></p>\n<p align=\"center\"><i><font color=\"#663300\">Linz - Freitag, 24. Juni 1988</font></i></p>\n<p align=\"left\"> <font face=\"Times New Roman\" size=\"3\"> </font></p>\n<p> </p>\n<p>1. Es ist schwer, ausdrucksstärkere Worte zu finden, als wir sie soeben aus den Klageliedern vernommen haben, die von der Überlieferung dem Propheten Jeremia zugeschrieben werden. </p>\n<p>Mehr als 40 Jahre sind vergangen seit jener Zeit, als die Todeslager, unter ihnen auch das von Mauthausen, Schaudern und Schrecken verbreiteten. Dies geschah im Herzen Europas. Dies geschah in der Mitte unseres Jahrhunderts, gegen Ende des Zweiten Jahrtausends nach Christus. </p>\n<p>Die Klagelieder des Jeremia künden den Messias und seine Leiden an. Sie sprechen von einem Menschen – einem Mann der Schmerzen –, dessen Kreuz auf Golgota, vor den Mauern der Heiligen Stadt Jerusalem aufgerichtet worden ist. Sie sprechen von Ihm – und in gewissem Sinn tun sie uns sogar seine eigenen Worte kund. Der Mund der Propheten, sein persönliches Schicksal, vermitteln uns diese besondere Botschaft. </p>\n<p>2. Gleichzeitig aber bringen diese Klagelieder eines Menschen auch die Leiden aller zum Ausdruck. Ja, von allen Menschen – besonders von denjenigen, die während der Jahre des fürchterlichen Weltkrieges in Europa durch die Qualen solcher Lager gegangen sind. </p>\n<p>Was der Prophet sagt, könnten die Lippen eines jeden von ihnen gesprochen haben. Und nicht nur ihre Lippen, sondern ihr ganzes inneres Menschsein, das hier so brutal getreten und unter den Lebensbedingungen des Lagers zur Vernichtung verdammt war. </p>\n<p>Dies sind Worte jeder menschlichen Seele, des Menschen der Schmerzen, der im ”Mann der Schmerzen“ der Bibel und des Evangeliums sein bleibendes Urbild findet. </p>\n<p>3. ”Ich bin der Mann, der Leid erlebt hat durch die Rute des Grimms. Er hat mich getrieben und gedrängt in Finsternis, nicht ins Licht. Täglich von neuem kehrt er die Hand nur gegen mich“.  Wer ist dieser ”Er“? </p>\n<p>Der Mensch also – der Gefangene von Mauthausen – erzählt sein eigenes Leiden. Und dieser Bericht ist zugleich eine Frage. Eine große Frage des Menschen aller Zeiten nach dem Leid. Verwandelt sich diese Frage nicht sogar in eine Anklage? </p>\n<p>Wer wird vom Mann der Schmerzen angeklagt? Wer wird von diesem gequälten Menschen, dem Gefangenen des Konzentrationslagers, unter Anklage gestellt? Oder... klagt er etwa Gott selbst an? – ”Ich bin der Mann, der Leid erlebt hat durch die Rute des Grimms“. </p>\n<p>”Er zehrte aus mein Fleisch und meine Haut, zerbrach meine Glieder“.  Hier an diesem Ort waren Menschen, die andere Menschen grausam mißhandelt haben... buchstäblich so, wie es die Klagelieder ankündigen. </p>\n<p>An diesem Ort, hier in Mauthausen, waren Menschen, die im Namen einer irrsinnigen Ideologie ein ganzes System der Verachtung und des Hasses gegen andere Menschen in Bewegung gesetzt haben. Sie unterzogen sie Folterungen, zerbrachen ihnen die Gebeine, mißhandelten grausam ihre Körper und Seelen. Sie verfolgten ihre Opfer in ihrer Grausamkeit. ”Sie umschlossen sie mit Gift und Erschöpfung. Im Finstern ließen diese sie wohnen wie längst Verstorbene“.  </p>\n<p>Auch hier haben sie jene ”ummauert“, die gefangengenommen und in diesem Lager eingesperrt waren. Sie haben sie ”in schwere Fesseln gelegt“, ihnen ”mit Quadern den Weg verriegelt“  in die Freiheit, zu ihrer Würde, zu den Grundrechten eines jeden Menschen, zum Leben... Hier setzte man auf den Tod, auf die Vernichtung eines jeden, den man für einen Gegner hielt. Und nicht nur das..., auch weil er nur ”verschieden“ war. Und vielleicht nur, weil er ein ”Mensch“ war? </p>\n<p>Der irrsinnige Plan, Europa auf den Wegen anzuhalten, auf denen es seit Jahrtausenden gegangen war! </p>\n<p>4. Sind wirklich ”die Wege verriegelt“ für die Völker, die Gesellschaft, für die Menschheit? Gewiß, Menschen sind zerschmettert worden. Sie sind – wie der Prophet sagt – ”mit bitterer Kost gespeist, mit Wermut getränkt“ und schließlich ”in den Staub gedrückt“ worden.  </p>\n<p>Hier... und an so vielen anderen Orten totalitärer Herrschaft. </p>\n<p>Aus dieser Erfahrung, eine der schrecklichsten seiner Geschichte, ist Europa besiegt hervorgegangen, ...besiegt in dem, was sein Erbe, seine Sendung zu sein schien... ”Seine Wege sind verriegelt“. Die Last des Zweifels hat sich schwer auf die Geschichte der Menschen, der Nationen, der Kontinente gelegt. </p>\n<p>Sind die Fragen des Gewissens stark genug – die Gewissensbisse, die uns geblieben sind? </p>\n<p>5. Ihr Menschen, die ihr furchtbare Qualen erfahren habt – welche der Klagelieder des Jeremia würdig sind! </p>\n<p>Welches ist euer letztes Wort? Euer Wort nach so vielen Jahren, die unsere Generation vom Leiden im Lager Mauthausen und in vielen anderen trennen? </p>\n<p>Mensch von gestern – und von heute, wenn das System der Vernichtungslager auch heute noch irgendwo in der Welt fortdauert, sage uns, was kann unser Jahrhundert an die nachfolgenden übermitteln? </p>\n<p>Sage uns, haben wir nicht mit allzu großer Eile deine Hölle vergessen? Löschen wir nicht in unserem Gedächtnis und Bewußtsein die Spuren der alten Verbrechen aus? </p>\n<p>Sage uns, in welche Richtung sollten sich Europa und die Menschheit ”nach Auschwitz“, ... ”nach Mauthausen“ entwickeln? Stimmt die Richtung, in die wir uns von den furchtbaren Erfahrungen von damals entfernen? </p>\n<p>Sage uns, wie sollte der Mensch sein und wie die Generation der Menschen, die hier aus den Spuren der großen Niederlage der Menschheit leben? Wie müßte der Mensch sein? Wieviel müßte er von sich selber fordern? </p>\n<p>Sage uns, wie müßten die Nationen und die Gesellschaften sein? Wie müßte Europa fortfahren zu leben? </p>\n<p>Rede, denn du hast das Recht dazu – du, der Mensch, der gelitten und das Leben verloren hat... Und wir müssen dein Zeugnis anhören. </p>\n<p>6. Haben nicht die Menschen und das von Menschen errichtete System mit dem Zorn Gottes Mißbrauch getrieben? </p>\n<p>Hat er nicht im Bewußtsein der Generationen sein Bild verdunkelt? </p>\n<p>Dennoch ruft der Prophet mit den Worten der Klagelieder: ”Die Huld des Herrn ist nicht erschöpft; sein Erbarmen ist nicht zu Ende. Neu ist es an jedem Morgen; groß ist deine Treue“.  </p>\n<p>Ja. Die Treue. Einer ist ”der Mann der Schmerzen“ der allen Menschen der Schmerzen treu gewesen ist, hier, in Mauthausen, und wo immer in der Welt sie durch ein unmenschliches System Verachtung erduldet haben oder noch erdulden. </p>\n<p>Es hat einen solchem Mann der Schmerzen gegeben. Und es gibt ihn weiterhin. In der Geschichte der Welt bleibt sein Kreuz gegenwärtig </p>\n<p>Dürfen wir uns von diesem Kreuz entfernen? Können wir an ihm vorbei in die Zukunft gehen? </p>\n<p>Europa, kannst du an ihm vorbeigehen? </p>\n<p>Mußt du nicht wenigstens bei ihm stehenbleiben, auch wenn die Generationen deiner Söhne und Töchter daran vorbeigehen und in die Vergangenheit entschwinden? </p>\n<p>7. Christus! Christus so vieler menschlicher Leiden, Demütigungen und Verwüstungen. Christus, gekreuzigt und auferstanden. An einem Ort – einem von so vielen –, die aus der Geschichte unseres Jahrhunderts nicht ausgelöscht werden können. </p>\n<p>Ich, der Bischof von Rom und Nachfolger deines Apostels Petrus, ich bitte dich inständig: Bleibe! </p>\n<p>Bleibe und lebe fort in unserer Zukunft! </p>\n<p>Bleibe und lebe fort! </p>\n<p>Wohin sollen wir gehen? Du hast Worte des Lebens, die der Tod nicht verhüllt, nicht zerstört hat... Du hast Worte ewigen Lebens.  </p>\n<p>Seliger Marcel Callo, Märtyrer von Mauthausen, selige Schwester Theresia Benedikta vom Kreuz, Edith Stein, und heiliger Pater Maximilian Kolbe, ihr gepriesenen und verehrten Märtyrer von Auschwitz, bittet für alle an diesen Orten des Todes Gequälten und Gemarterten! Bittet für alle Opfer ungerechter Gewalt, gestern und heute – bittet auch für ihre Henker! </p>\n<p>Jesus Christus, Lamm Gottes, erbarme dich ihrer aller – erbarme dich unser aller! </p>\n<p align=\"left\">  </p>\n<p align=\"center\"> <font color=\"#663300\" face=\"Times New Roman\" size=\"3\">© Copyright 1988 - Libreria Editrice Vaticana</font><font face=\"Times New Roman\" size=\"3\"></font></p>\n<p align=\"center\">  </p><div class=\"clearfix\"></div></div>\n</div>\n<!-- /TESTO -->\n<br style=\"clear: both;\"/>\n<hr/>\n<p align=\"center\"><font color=\"#663300\">Copyright © Dicastero per la Comunicazione - Libreria Editrice Vaticana</font></p>\n<!-- /CONTENUTO DOCUMENTO -->\n</div>",
            "it": "<div class=\"documento\">\n<!-- CONTENUTO DOCUMENTO -->\n<!-- TESTO -->\n<div class=\"testo\">\n<div class=\"abstract text parbase vaticanrichtext\"><div class=\"clearfix\"></div></div>\n<div class=\"text parbase container vaticanrichtext\"><p align=\"center\"><font color=\"#663300\">VISITA PASTORALE IN AUSTRIA</font></p>\n<p align=\"center\"><font color=\"#663300\" size=\"4\"><b><i>INCONTRO</i></b></font><b><i><font color=\"#663300\" size=\"4\"> DI GIOVANNI PAOLO II CON ALCUNI SUPERSTITI<br>NELL</br></font></i><font color=\"#663300\" size=\"4\"><i>’EX CAMPO DI CONCENTRAMENTO DI MAUTHAUSEN</i></font></b></p>\n<p align=\"center\"><font color=\"#663300\"><i>Linz</i></font><i><font color=\"#663300\"> - Venerdì, 24 giugno 1988</font></i></p>\n<p> </p>\n<p>1. È difficile trovare espressioni più forti, dopo aver appena ascoltato le lamentazioni che la tradizione attribuisce al profeta Geremia. </p>\n<p>Sono passati più di quarant’anni da quando i campi di sterminio, tra i quali anche quello di Mauthausen, incutevano terrore e sgomento. E tutto ciò accadeva nel cuore dell’Europa. Tutto ciò nel mezzo del nostro secolo, verso la fine del secondo millennio dopo Cristo. </p>\n<p>Le lamentazioni di Geremia annunciano l’avvento del Messia e le sue sofferenze. Parlano di un uomo - l’uomo dei dolori - la cui croce sul Golgota è stata innalzata di fronte alle mura della città santa di Gerusalemme. </p>\n<p>Le lamentazioni parlano di lui - e in un certo senso ce lo fanno conoscere con le sue stesse parole. Le parole del profeta, il suo destino personale, ci trasmettono questo particolare messaggio. </p>\n<p>2. Contemporaneamente però queste lamentazioni di un uomo esprimono i dolori di tutti. Sì, di tutti gli uomini particolarmente di quelli che durante gli anni della spaventosa guerra mondiale in Europa hanno patito i supplizi di simili campi di concentramento. </p>\n<p>Quello che dice il profeta, potrebbero averlo espresso le labbra di ciascuno di loro. E non solo le loro labbra, ma anche la loro intima essenza umana, che qui è stata così brutalmente calpestata e condannata all’annientamento nelle terribili condizioni di vita del campo di sterminio. </p>\n<p>Queste sono le parole di ciascuna anima umana, dell’uomo dei dolori, che trova il suo archetipo permanente nell’“uomo dei dolori” della Bibbia e del Vangelo. </p>\n<p>3. “Io sono l’uomo che ha provato la miseria sotto la sferza della sua ira. Egli mi ha guidato, mi ha fatto camminare nelle tenebre e non nella luce. Solo contro di me egli ha volto e rivolto la sua mano tutto il giorno” (<i>Lam</i> 3, 1-3). A chi è riferito questo “egli”? </p>\n<p>Anche l’uomo - quello prigioniero nel campo di concentramento di Mauthausen - racconta le sue personali sofferenze. E questo riferire è allo stesso tempo una domanda. Una inquietante domanda dell’uomo di tutti i tempi nei confronti del dolore. Ma questa domanda non si muta forse in un’accusa? </p>\n<p>Chi viene accusato dall’uomo dei dolori? Chi viene incolpato da quella creatura martoriata, dal prigioniero del campo di sterminio? O forse . . . egli accusa in qualche modo Dio stesso? - “Io sono l’uomo che ha provato la miseria sotto la sferza della sua ira”. “Egli ha consumato la mia carne e la mia pelle, ha rotto le mie ossa” (<i>Lam</i> 3, 4) in questo luogo ci sono stati uomini che hanno torturato altri uomini . . . così come preannunciano le Lamentazioni. </p>\n<p>In questo luogo, a Mauthausen, vi sono stati esseri umani che in nome delle loro folli ideologie hanno creato un intero sistema di annientamento e di odio nei confronti di altri esseri umani. Li hanno sottoposti a torture incredibili, hanno spezzato loro le ossa, hanno infierito selvaggiamente sui loro corpi e le loro anime: hanno perseguitato le loro vittime con crudeltà. “Ha costruito sopra di me, mi ha circondato di veleno e di affanno. Mi ha fatto abitare in luoghi tenebrosi come i morti da lungo tempo” (cf. <i>Lam</i> 3, 5-6). </p>\n<p>Anche qui essi hanno “murato” tutti coloro che erano stati fatti prigionieri e rinchiusi in questi lager. Anche qui essi hanno “reso pesanti le catene” e hanno “sbarrato le vie con blocchi di pietra” (cf. <i>Lam</i> 3, 7. 9) le vie della libertà, della dignità, dei diritti fondamentali di ogni essere umano, della vita stessa . . . Qui si progettava la morte, l’annientamento più totale di chi si reputava nemico. E non solo questo . . ., forse anche perché era reputato “diverso”. O forse solo perché era un “uomo”? </p>\n<p>Il piano empio era di far tornare l’Europa su vie che erano state percorse da migliaia di anni! </p>\n<p>4. Ma è vero che le “strade sono sbarrate” per i popoli, per la società, per l’umanità? Certamente l’essere umano è stato annientato. Egli è - come dice il profeta - “saziato con erbe amare, dissetato con assenzio” e per concludere “steso nella polvere” (cf. <i>Lam</i> 3, 15. 16). Questo è accaduto qui e accade . . . in tante altre nazioni a regime totalitario. </p>\n<p>Da questa vicenda, una delle più agghiaccianti della sua storia, l’Europa esce sconfitta . . . sconfitta in quella che sembra invece essere la sua eredità, la sua missione . . . “Le sue strade sono sbarrate”. Il peso del dubbio grava sulla storia degli uomini, delle nazioni, dei continenti. </p>\n<p>Gli interrogativi delle nostre coscienze, il fardello del rimorso che ci sono rimasti, sono abbastanza pressanti? </p>\n<p>5. Voi uomini che avete vissuto in prima persona quei terribili supplizi quanto siete degni delle lamentazioni di Geremia! Qual è la vostra ultima parola? Qual è la vostra parola pronunciata dopo tanti anni che separano la nostra generazione dalle sofferenze vissute nel campo di concentramento di Mauthausen e in tanti altri? </p>\n<p>Uomini di ieri e di oggi diteci: cosa mai può tramandare ai posteri il nostro secolo, se persiste ancora oggi in qualche parte del mondo il sistema dei campi di sterminio? </p>\n<p>Diteci, abbiamo forse noi dimenticato con troppa fretta il vostro inferno? Non spegniamo forse nelle nostre menti e nelle nostre coscienze le tracce di quei vecchi crimini? </p>\n<p>Diteci ancora, in quale direzione dovrebbero andare l’Europa e la umanità tutta “dopo Auschwitz” . . . “dopo Mauthausen”? È giusta la direzione nella quale ci allontaniamo da quelle orribili esperienze del passato? </p>\n<p>Diteci, come dovrebbe essere l’uomo di oggi e le generazioni che vivono sulle rovine dell’immensa sconfitta dell’essere umano? </p>\n<p>Come dovrebbe essere quell’uomo? Cosa dovrebbe esigere da se stesso? </p>\n<p>Diteci, come dovrebbero essere secondo voi le nazioni e le società? In che modo l’Europa dovrebbe continuare a vivere? Parla, perché ne hai il diritto - parla uomo che hai sopportato tanto e hai perso la vita . . . Parla e noi abbiamo il dovere di ascoltare la tua testimonianza. </p>\n<p>6. Non credete che l’uomo e il meccanismo da lui ideato abbiano sfidato la collera di Dio? </p>\n<p>Non credete che l’uomo abbia oscurato l’immagine di Dio nelle coscienze delle generazioni? </p>\n<p>Tuttavia dice il profeta con le parole delle Lamentazioni: “Le misericordie del Signore non sono finite, non è esaurita la sua compassione; esse sono rinnovate ogni mattina” (<i>Lam</i> 3, 22-23). </p>\n<p>La fedeltà. Uno solo e “l’Uomo dei dolori” che non ha mai abbandonato tutti gli uomini che soffrono, qui a Mauthausen e ovunque nel mondo essi abbiano sopportato o sopportino ancora l’annientamento causato da un sistema disumano. </p>\n<p>È esistito e continua ad esistere un tale uomo dei dolori. Nella storia del mondo la sua croce resta presente. </p>\n<p>Abbiamo noi il diritto di allontanarci da questa croce? Possiamo noi in futuro passare dinnanzi ad essa senza guardarla? </p>\n<p>Europa, puoi forse procedere senza questa croce? </p>\n<p>Non devi restare accanto a lui anche quando le generazioni dei tuoi figli e delle tue figlie se ne allontanano e il passato svanisce? </p>\n<p>7. Cristo! Cristo di tante sofferenze, umiliazioni e devastazioni dell’uomo. Cristo, crocifisso e risorto. In questo luogo, uno dei tanti che non possono essere cancellati dalla storia di questo secolo. Io, il Vescovo di Roma e il successore del tuo apostolo Pietro, ti prego fervidamente: resta! </p>\n<p>Resta e continua a vivere nel nostro futuro! </p>\n<p>Resta e continua a vivere! </p>\n<p>Dove dobbiamo andare? Tu hai parole di vita, che la morte non ha appannato o distrutto . . . Tu hai parole di vita eterna (cf. <i>Gv</i> 6, 68). </p>\n<p>Il beato Marcello Callo, martire di Mauthausen, la beata suor Teresa Benedetta della Croce Edith Stein, e san Massimiliano Kolbe, voi onorati e venerati martiri di Auschwitz, pregate per tutti coloro che sono stati seviziati e martirizzati in questi luoghi di morte! </p>\n<p>Pregate per ogni vittima di un potere ingiusto, di ieri e di oggi, pregate anche per i loro carnefici! </p>\n<p>Gesù Cristo, Agnello di Dio, abbi pietà di loro e di noi tutti! </p>\n<hr>\n<p><i>Sull’aereo che lo porta da Vienna a Linz, il Santo Padre ricorda Dante Alimenti, il giornalista del TG-1 che lo ha accompagnato nel corso di tutti i suoi viaggi, deceduto a Roma. Queste le parole pronunciate da Giovanni Paolo II. </i> </p>\n<p>Alle cinque di oggi pomeriggio si celebrano i funerali del caro amico Dante Alimenti. Ha tante volte viaggiato con noi in questi viaggi. Ha molto collaborato con noi, con il Papa. Rimango profondamente riconoscente alla sua persona e anche profondamente legato alla sua famiglia cui ho già trasmesso le espressioni della mia compassione. Siamo tutti invitati a pregare per questa persona così vicina e così cara a noi tutti. </p>\n<p align=\"left\">  </p>\n<p align=\"center\"> <font color=\"#663300\" face=\"Times New Roman\" size=\"3\">© Copyright 1988 - Libreria Editrice Vaticana</font><font face=\"Times New Roman\" size=\"3\"></font></p>\n<p align=\"center\">  </p><div class=\"clearfix\"></div></hr></div>\n</div>\n<!-- /TESTO -->\n<br style=\"clear: both;\"/>\n<hr/>\n<p align=\"center\"><font color=\"#663300\">Copyright © Dicastero per la Comunicazione - Libreria Editrice Vaticana</font></p>\n<!-- /CONTENUTO DOCUMENTO -->\n</div>"
        }
    }
}